MANIFEST.in
README
requirements.txt
setup.py
boopyboop/__init__.py
boopyboop.egg-info/PKG-INFO
boopyboop.egg-info/SOURCES.txt
boopyboop.egg-info/dependency_links.txt
boopyboop.egg-info/requires.txt
boopyboop.egg-info/top_level.txt