Metadata-Version: 1.1
Name: boopyboop
Version: 0.0.8
Summary: Turn long numbers in whatever format to human-readable long series of words
Home-page: https://github.com/howonlee/boopyboop
Author: Howon Lee
Author-email: howon@howonlee.com
License: MIT
Platform: UNKNOWN
Classifier: Development Status :: 3 - Alpha
Classifier: License :: OSI Approved :: MIT License
